MoMPy/BloM.py
MoMPy/MoM.py
MoMPy/__init__.py
MoMPy/blkdiag.py
mompy-0.2.1.dist-info/METADATA
mompy-0.2.1.dist-info/WHEEL
mompy-0.2.1.dist-info/licenses/LICENSE.md
mompy-0.2.1.dist-info/RECORD
