Metadata-Version: 2.4
Name: MoMPy
Version: 0.2.1
Summary: Moment matrix generation package for SDP hierarchies
Project-URL: Homepage, https://github.com/chalswater/MoMPy
Author-email: Carles Roch i Carceller <chalswater@gmail.com>
License-Expression: MIT
License-File: LICENSE.md
Keywords: SDP hierarchy,moment matrix,quantum correlations,semidefinite programming
Classifier: License :: OSI Approved :: MIT License
Classifier: Operating System :: OS Independent
Classifier: Programming Language :: Python :: 3
Requires-Python: >=3.8
Requires-Dist: numpy
